LICENSE
MANIFEST.in
README.md
setup.py
tap_pepperjam/__init__.py
tap_pepperjam/client.py
tap_pepperjam/discover.py
tap_pepperjam/schema.py
tap_pepperjam/streams.py
tap_pepperjam/sync.py
tap_pepperjam/transform.py
tap_pepperjam.egg-info/PKG-INFO
tap_pepperjam.egg-info/SOURCES.txt
tap_pepperjam.egg-info/dependency_links.txt
tap_pepperjam.egg-info/entry_points.txt
tap_pepperjam.egg-info/requires.txt
tap_pepperjam.egg-info/top_level.txt
tap_pepperjam/schemas/creative_advanced.json
tap_pepperjam/schemas/creative_banner.json
tap_pepperjam/schemas/creative_coupon.json
tap_pepperjam/schemas/creative_generic.json
tap_pepperjam/schemas/creative_performance.json
tap_pepperjam/schemas/creative_performance_by_publisher.json
tap_pepperjam/schemas/creative_product.json
tap_pepperjam/schemas/creative_promotion.json
tap_pepperjam/schemas/creative_text.json
tap_pepperjam/schemas/group.json
tap_pepperjam/schemas/group_member.json
tap_pepperjam/schemas/itemized_list.json
tap_pepperjam/schemas/itemized_list_product.json
tap_pepperjam/schemas/publisher.json
tap_pepperjam/schemas/publisher_performance.json
tap_pepperjam/schemas/term.json
tap_pepperjam/schemas/transaction_details.json
tap_pepperjam/schemas/transaction_history.json