Metadata-Version: 1.1
Name: tap-pepperjam
Version: 1.0.0
Summary: Singer.io tap for extracting data from the Pepperjam Advertiser API
Home-page: UNKNOWN
Author: jeff.huth@bytecode.io
Author-email: UNKNOWN
License: UNKNOWN
Platform: UNKNOWN
Classifier: Programming Language :: Python :: 3 :: Only
